[
  {
    "threadID": "5996726197081077",
    "data": [
      {
        "name": "Tihonkha Fruit",
        "id": "100076693913697",
        "exp": 28
      },
      {
        "name": "Lê Đình Trường",
        "id": "100081320911618",
        "exp": 15
      },
      {
        "name": "Nguyen Đức Anh",
        "id": "100090306996593",
        "exp": 6
      },
      {
        "name": "Hieu Trong",
        "id": "100089610244121",
        "exp": 0
      },
      {
        "name": "Lê Thị Ngọc Như",
        "id": "100087506686573",
        "exp": 0
      },
      {
        "name": "Nguyễn Ngọc Trâm",
        "id": "100091368309431",
        "exp": 10
      },
      {
        "name": "Lường Tuấn Tú",
        "id": "100076065709699",
        "exp": 0
      },
      {
        "name": "Linh Ttnl",
        "id": "100031611200491",
        "exp": 0
      },
      {
        "name": "Trung Kien",
        "id": "100071207794840",
        "exp": 2
      },
      {
        "name": "Việt Bách",
        "id": "100086354397331",
        "exp": 0
      },
      {
        "name": "Nguyễn Việt",
        "id": "100088042436601",
        "exp": 0
      },
      {
        "name": "Yến Nhi",
        "id": "100073740590624",
        "exp": 0
      },
      {
        "name": "Dumbo Vũ",
        "id": "100085601766744",
        "exp": 0
      },
      {
        "name": "Bảo Nam",
        "id": "100080044928605",
        "exp": 0
      },
      {
        "name": "Quang Vanh Lê",
        "id": "100089103375142",
        "exp": 14
      },
      {
        "name": "Hưng Wibu",
        "id": "100082600626898",
        "exp": 0
      },
      {
        "name": "Trần Dũng",
        "id": "100075850404633",
        "exp": 0
      },
      {
        "name": "Ng Hồng Sơn",
        "id": "100045948857642",
        "exp": 2
      },
      {
        "name": "Phạm Đức Duy",
        "id": "100077582630093",
        "exp": 0
      },
      {
        "name": "Nguyễn Đạt",
        "id": "100085601026836",
        "exp": 0
      },
      {
        "name": "Nguyễn Nhật Thiện",
        "id": "100078447173703",
        "exp": 0
      },
      {
        "name": "Ngọc Minh",
        "id": "100076543178636",
        "exp": 0
      },
      {
        "name": "Hồ Đạt",
        "id": "100075212572579",
        "exp": 49
      },
      {
        "name": "Khanh Shado",
        "id": "100064267053853",
        "exp": 52
      },
      {
        "name": "Ng Văn Chiến ",
        "id": "100048286966787",
        "exp": 9
      },
      {
        "name": "Khanh Shado",
        "id": "100090458979503",
        "exp": 64
      },
      {
        "name": "Phạm Hoàng Bảo",
        "id": "100080435726504",
        "exp": 0
      }
    ]
  },
  {
    "threadID": "6048419705243431",
    "data": [
      {
        "name": "Duy Tần",
        "id": "100082172861464",
        "exp": 0
      },
      {
        "name": "Trần Bảo Nam",
        "id": "100072764588408",
        "exp": 0
      },
      {
        "name": "Văn Hải",
        "id": "100084368957984",
        "exp": 0
      },
      {
        "name": "Manh Nặng Mạnh",
        "id": "100080490429213",
        "exp": 0
      },
      {
        "name": "Bọ Báo Tử",
        "id": "100070299475995",
        "exp": 0
      },
      {
        "name": "Tuân Anh Phan",
        "id": "100073229750306",
        "exp": 0
      },
      {
        "name": "Bao Tran",
        "id": "100069083905450",
        "exp": 0
      },
      {
        "name": "Tí Chuột",
        "id": "100090508784322",
        "exp": 0
      },
      {
        "name": "Khanh Shado",
        "id": "100090458979503",
        "exp": 3
      },
      {
        "name": "Hiếu Nguyễn",
        "id": "100074875400035",
        "exp": 0
      },
      {
        "name": "Phúc Huy",
        "id": "100080259123431",
        "exp": 0
      },
      {
        "name": "Ngô Hải Châu",
        "id": "100063218863151",
        "exp": 0
      },
      {
        "name": "Dũng Hà",
        "id": "100090001233850",
        "exp": 0
      },
      {
        "name": "Thuowg Sad",
        "id": "100076679529684",
        "exp": 0
      },
      {
        "name": " Đoàn Văn Hậu",
        "id": "100004366982560",
        "exp": 0
      },
      {
        "name": "Đặng Nam Hải Triều",
        "id": "100087428784586",
        "exp": 0
      },
      {
        "name": "Anonymus",
        "id": "100086767989219",
        "exp": 0
      },
      {
        "name": "Mạc Văn Khoa",
        "id": "100011050260447",
        "exp": 0
      },
      {
        "name": "Anh Ba Phải Coffee",
        "id": "100087500270279",
        "exp": 0
      },
      {
        "name": "Ahmad Kaiber",
        "id": "100050215098698",
        "exp": 0
      },
      {
        "name": "Eimi Fukuda",
        "id": "100060578889393",
        "exp": 0
      },
      {
        "name": "HeavyNa Gây Mê",
        "id": "100085593971559",
        "exp": 0
      },
      {
        "name": "Vtvdanang Vtv",
        "id": "100006688273577",
        "exp": 0
      },
      {
        "name": "Anh Áo Den",
        "id": "100089815664862",
        "exp": 0
      },
      {
        "name": "Vũ Bồ Phúc",
        "id": "100000119437845",
        "exp": 0
      },
      {
        "name": "Trúc Đào",
        "id": "100012162669906",
        "exp": 0
      },
      {
        "name": "Huy Seoul",
        "id": "100000387426107",
        "exp": 0
      },
      {
        "name": "Hoàng Hưng HQ",
        "id": "100064904745662",
        "exp": 5
      },
      {
        "name": "Minh Hiếu",
        "id": "100088586648039",
        "exp": 0
      },
      {
        "name": "Nam Nguyen",
        "id": "100068785179667",
        "exp": 0
      },
      {
        "name": "Doan Hai My",
        "id": "100040911668087",
        "exp": 0
      },
      {
        "name": "Quế Ngọc Hải",
        "id": "100002959340724",
        "exp": 0
      },
      {
        "name": "Nguyễn Phạm Tường Vy",
        "id": "100005237762037",
        "exp": 0
      },
      {
        "name": "Ngô Tố Uyên",
        "id": "100012112810727",
        "exp": 0
      },
      {
        "name": "Bác Gấu",
        "id": "100087336636149",
        "exp": 0
      },
      {
        "name": "Adijatu Kuburatu Adejoke Osho",
        "id": "100024323362035",
        "exp": 0
      },
      {
        "name": "Phạm Thị Phương Quỳnh",
        "id": "100005321204448",
        "exp": 0
      },
      {
        "name": "Nguyễn Hữu Dũng",
        "id": "100000369423339",
        "exp": 0
      },
      {
        "name": "Phong Tran",
        "id": "100075061185489",
        "exp": 0
      },
      {
        "name": "Duy Nguyen",
        "id": "100083922338456",
        "exp": 0
      },
      {
        "name": "Nguyễn Thắng",
        "id": "100033645221041",
        "exp": 0
      },
      {
        "name": "Dũng Nguyễn",
        "id": "100069527982717",
        "exp": 0
      },
      {
        "name": "Bolox Fruit Hoàng",
        "id": "100087525513652",
        "exp": 0
      },
      {
        "name": "Hoàng Bi",
        "id": "100044815774365",
        "exp": 0
      },
      {
        "name": "Hoàng Diệp Phú",
        "id": "100081606611681",
        "exp": 0
      },
      {
        "name": "Mít Tơ Bảo",
        "id": "100074128454173",
        "exp": 0
      },
      {
        "name": "Khanh Shado",
        "id": "100064267053853",
        "exp": 1
      }
    ]
  },
  {
    "threadID": "7469714026394342",
    "data": [
      {
        "name": "Seend Glass Sarah",
        "id": "100094957762135",
        "exp": 14
      },
      {
        "name": "Sarah Glass",
        "id": "61555323331885",
        "exp": 8
      },
      {
        "name": "Ngột Hetcuu",
        "id": "100087059451078",
        "exp": 3
      },
      {
        "name": "Người dùng Facebook",
        "id": "61553973584944",
        "exp": 5
      },
      {
        "name": "Dương Ngọc",
        "id": "100078244687856",
        "exp": 1
      }
    ]
  }
]